pyucis_viewer/__init__.py
pyucis_viewer/__main__.py
pyucis_viewer/coverage_data_tree.py
pyucis_viewer/coverage_tree_model.py
pyucis_viewer/data_model.py
pyucis_viewer/data_model_listener.py
pyucis_viewer/instance_tree.py
pyucis_viewer/instance_tree_model.py
pyucis_viewer/main_window.py
pyucis_viewer-0.0.4.2612514264.dist-info/LICENSE
pyucis_viewer-0.0.4.2612514264.dist-info/METADATA
pyucis_viewer-0.0.4.2612514264.dist-info/WHEEL
pyucis_viewer-0.0.4.2612514264.dist-info/entry_points.txt
pyucis_viewer-0.0.4.2612514264.dist-info/top_level.txt
pyucis_viewer-0.0.4.2612514264.dist-info/RECORD
